homekit_mqtt/__init__.py
homekit_mqtt/adapters.py
homekit_mqtt/cfg_loader.py
homekit_mqtt/cli.py
homekit_mqtt/mqtt_bridge.py
homekit_mqtt/tasmota.py
homekit_mqtt/data/bridge.cfg
homekit_mqtt/data/homekit-mqtt.service
homekit_mqtt-0.1.10.dist-info/DESCRIPTION.rst
homekit_mqtt-0.1.10.dist-info/METADATA
homekit_mqtt-0.1.10.dist-info/RECORD
homekit_mqtt-0.1.10.dist-info/WHEEL
homekit_mqtt-0.1.10.dist-info/entry_points.txt
homekit_mqtt-0.1.10.dist-info/metadata.json
homekit_mqtt-0.1.10.dist-info/top_level.txt
